pytineye/__init__.py
pytineye/api.py
pytineye/exceptions.py
test/__init__.py
test/test_api.py
pytineye-3.0.0.dist-info/LICENSE
pytineye-3.0.0.dist-info/METADATA
pytineye-3.0.0.dist-info/WHEEL
pytineye-3.0.0.dist-info/top_level.txt
pytineye-3.0.0.dist-info/RECORD
