Metadata-Version: 2.1
Name: pytineye
Version: 3.0.0
Summary: Python client for the TinEye API.
Home-page: https://api.tineye.com/
Author: TinEye
Author-email: support@tineye.com
License: MIT License
Project-URL: Documentation, https://api.tineye.com/python/docs/
Project-URL: Source, https://github.com/TinEye/pytineye/
Keywords: tineye,api,reverse image search
Platform: UNKNOWN
Classifier: Intended Audience :: Developers
Classifier: Programming Language :: Python :: 2.7
Classifier: Programming Language :: Python :: 3.5
Classifier: Programming Language :: Python :: 3.6
Classifier: Programming Language :: Python :: 3.7
Classifier: Programming Language :: Python :: 3.8
Classifier: Programming Language :: Python :: 3.9
License-File: LICENSE
